jwl_rpcm/__about__.py
jwl_rpcm/__init__.py
jwl_rpcm/cli.py
jwl_rpcm/geo.py
jwl_rpcm/rpc_file_readers.py
jwl_rpcm/rpc_model.py
jwl_rpcm/utils.py
jwl_rpcm-1.4.8.dist-info/LICENSE
jwl_rpcm-1.4.8.dist-info/METADATA
jwl_rpcm-1.4.8.dist-info/WHEEL
jwl_rpcm-1.4.8.dist-info/entry_points.txt
jwl_rpcm-1.4.8.dist-info/top_level.txt
jwl_rpcm-1.4.8.dist-info/RECORD
