Metadata-Version: 2.1
Name: jwl-rpcm
Version: 1.4.8
Summary: Rational Polynomial Camera Model for optical satellite images.
Home-page: https://github.com/centreborelli/rpcm
Author: Carlo de Franchis
Author-email: carlo.de-franchis@ens-paris-saclay.fr
Requires-Python: >=3
License-File: LICENSE
Requires-Dist: numpy
Requires-Dist: pyproj
Requires-Dist: geojson
Requires-Dist: rasterio[s3] (>=1.2)
Requires-Dist: srtm4 (>=1.0.2)
Provides-Extra: test
Requires-Dist: pytest ; extra == 'test'
